focalnet/__init__.py
focalnet/download_weights.py
focalnet/drop.py
focalnet/focalnet.py
focalnet/focalnet_utils.py
focalnet/imagenet-1k.json
focalnet/imagenet-21k.json
focalnet/imagenet-22k-reorder.json
focalnet_tf-0.0.2.3.dist-info/LICENSE
focalnet_tf-0.0.2.3.dist-info/METADATA
focalnet_tf-0.0.2.3.dist-info/WHEEL
focalnet_tf-0.0.2.3.dist-info/top_level.txt
focalnet_tf-0.0.2.3.dist-info/RECORD
