Metadata-Version: 2.1
Name: focalnet-tf
Version: 0.0.2.3
Summary: Re-implementation of FocalNet for tensorflow 2.X
Home-page: https://github.com/Shiro-LK/focalnet-tf
Download-URL: https://github.com/Shiro-LK/focalnet-tf.git
Author: Shiro-LK
Author-email: shirosaki94@gmail.com
License: MIT License
Keywords: focalnet,tensorflow
Classifier: Development Status :: 5 - Production/Stable
Classifier: Programming Language :: Python :: 3.7
Classifier: Programming Language :: Python :: 3.8
License-File: LICENSE
Requires-Dist: numpy
Requires-Dist: pytest
Requires-Dist: tensorflow
Requires-Dist: opencv-python
